dtool_lookup_server_direct_mongo_plugin/__init__.py
dtool_lookup_server_direct_mongo_plugin/config.py
dtool_lookup_server_direct_mongo_plugin/schemas.py
dtool_lookup_server_direct_mongo_plugin/utils.py
dtool_lookup_server_direct_mongo_plugin-0.2.0.dist-info/LICENSE
dtool_lookup_server_direct_mongo_plugin-0.2.0.dist-info/METADATA
dtool_lookup_server_direct_mongo_plugin-0.2.0.dist-info/WHEEL
dtool_lookup_server_direct_mongo_plugin-0.2.0.dist-info/entry_points.txt
dtool_lookup_server_direct_mongo_plugin-0.2.0.dist-info/top_level.txt
dtool_lookup_server_direct_mongo_plugin-0.2.0.dist-info/RECORD
